{
    "prefix": "REQUESTS_PAGE",
    "en": {
        "Title": "Requests",
        "State": "State",
        "StatePending": "Pending",
        "StateAccepted": "Accepted",
        "StateRejected": "Rejected",
        "StateCompleted": "Completed",
        "NoRequests": "No requests available",
        "Line": "Line",
        "Bus": "Bus",
        "Time": "approximated pick up time",
        "ASTitle": "Options",
        "ASCancelRequest": "Cancel Request",
        "ASBack": "Back"
    },
    "de": {
        "Title": "Haltewünsche",
        "State": "Status",
        "StatePending": "Wartend",
        "StateAccepted": "Angenommen",
        "StateRejected": "Abgelehnt",
        "StateCompleted": "Erfüllt",
        "NoRequests": "Keine Haltewünsche verfügbar",
        "Line": "Linie",
        "Bus": "Bus",
        "Time": "Erwartete Ankunft",
        "ASTitle": "Optionen",
        "ASCancelRequest": "Anfrage widerrufen",
        "ASBack": "Zurück"
    }
}